rpki_ov_checker/__init__.py
rpki_ov_checker/checker.py
rpki_ov_checker/ov.py
rpki_ov_checker-0.0.1.dist-info/LICENSE
rpki_ov_checker-0.0.1.dist-info/METADATA
rpki_ov_checker-0.0.1.dist-info/WHEEL
rpki_ov_checker-0.0.1.dist-info/entry_points.txt
rpki_ov_checker-0.0.1.dist-info/top_level.txt
rpki_ov_checker-0.0.1.dist-info/RECORD
