Metadata-Version: 2.1
Name: rpki-ov-checker
Version: 0.0.1
Summary: RPKI Origin Validation checker
Home-page: https://github.com/job/rpki-ov-checker
Maintainer: Job Snijders
Maintainer-email: job@ntt.net
License: BSD
Keywords: rpki prefix routing networking
Platform: UNKNOWN
Classifier: Intended Audience :: Developers
Classifier: Topic :: Software Development :: Libraries :: Python Modules
Classifier: Topic :: System :: Networking
Classifier: License :: OSI Approved :: BSD License
Classifier: Programming Language :: Python :: 3 :: Only
Requires-Dist: requests
Requires-Dist: py-radix
